astronauth/__init__.py
astronauth/_version.py
astronauth/apps.py
astronauth/urls.py
astronauth/static/astronauth/css/custom.css
astronauth/static/astronauth/css/dias.css
astronauth/static/astronauth/fonts/Raleway/OFL.txt
astronauth/static/astronauth/fonts/Raleway/README.txt
astronauth/static/astronauth/fonts/Raleway/Raleway-Italic-VariableFont_wght.ttf
astronauth/static/astronauth/fonts/Raleway/Raleway-VariableFont_wght.ttf
astronauth/static/astronauth/fonts/Raleway/static/Raleway-Black.ttf
astronauth/static/astronauth/fonts/Raleway/static/Raleway-BlackItalic.ttf
astronauth/static/astronauth/fonts/Raleway/static/Raleway-Bold.ttf
astronauth/static/astronauth/fonts/Raleway/static/Raleway-BoldItalic.ttf
astronauth/static/astronauth/fonts/Raleway/static/Raleway-ExtraBold.ttf
astronauth/static/astronauth/fonts/Raleway/static/Raleway-ExtraBoldItalic.ttf
astronauth/static/astronauth/fonts/Raleway/static/Raleway-ExtraLight.ttf
astronauth/static/astronauth/fonts/Raleway/static/Raleway-ExtraLightItalic.ttf
astronauth/static/astronauth/fonts/Raleway/static/Raleway-Italic.ttf
astronauth/static/astronauth/fonts/Raleway/static/Raleway-Light.ttf
astronauth/static/astronauth/fonts/Raleway/static/Raleway-LightItalic.ttf
astronauth/static/astronauth/fonts/Raleway/static/Raleway-Medium.ttf
astronauth/static/astronauth/fonts/Raleway/static/Raleway-MediumItalic.ttf
astronauth/static/astronauth/fonts/Raleway/static/Raleway-Regular.ttf
astronauth/static/astronauth/fonts/Raleway/static/Raleway-SemiBold.ttf
astronauth/static/astronauth/fonts/Raleway/static/Raleway-SemiBoldItalic.ttf
astronauth/static/astronauth/fonts/Raleway/static/Raleway-Thin.ttf
astronauth/static/astronauth/fonts/Raleway/static/Raleway-ThinItalic.ttf
astronauth/static/astronauth/fonts/icons/icon-dias.eot
astronauth/static/astronauth/fonts/icons/icon-dias.svg
astronauth/static/astronauth/fonts/icons/icon-dias.ttf
astronauth/static/astronauth/fonts/icons/icon-dias.woff
astronauth/static/astronauth/images/astronauth.svg
astronauth-0.3.3.dist-info/LICENSE
astronauth-0.3.3.dist-info/METADATA
astronauth-0.3.3.dist-info/WHEEL
astronauth-0.3.3.dist-info/top_level.txt
astronauth-0.3.3.dist-info/RECORD
